CHANGELOG.md
LICENSE
MANIFEST.in
Makefile
README.md
setup.cfg
setup.py
tox.ini
px_django_massaffect.egg-info/PKG-INFO
px_django_massaffect.egg-info/SOURCES.txt
px_django_massaffect.egg-info/dependency_links.txt
px_django_massaffect.egg-info/requires.txt
px_django_massaffect.egg-info/top_level.txt
pxd_massaffect/__init__.py
pxd_massaffect/admin.py
pxd_massaffect/affector.py
pxd_massaffect/apps.py
pxd_massaffect/conf.py
pxd_massaffect/const.py
pxd_massaffect/models.py
pxd_massaffect/registry.py
pxd_massaffect/builtins/__init__.py
pxd_massaffect/builtins/excludable.py
pxd_massaffect/locale/af/LC_MESSAGES/django.mo
pxd_massaffect/locale/af/LC_MESSAGES/django.po
pxd_massaffect/locale/ar/LC_MESSAGES/django.mo
pxd_massaffect/locale/ar/LC_MESSAGES/django.po
pxd_massaffect/locale/ast/LC_MESSAGES/django.mo
pxd_massaffect/locale/ast/LC_MESSAGES/django.po
pxd_massaffect/locale/az/LC_MESSAGES/django.mo
pxd_massaffect/locale/az/LC_MESSAGES/django.po
pxd_massaffect/locale/be/LC_MESSAGES/django.mo
pxd_massaffect/locale/be/LC_MESSAGES/django.po
pxd_massaffect/locale/bg/LC_MESSAGES/django.mo
pxd_massaffect/locale/bg/LC_MESSAGES/django.po
pxd_massaffect/locale/bn/LC_MESSAGES/django.mo
pxd_massaffect/locale/bn/LC_MESSAGES/django.po
pxd_massaffect/locale/br/LC_MESSAGES/django.mo
pxd_massaffect/locale/br/LC_MESSAGES/django.po
pxd_massaffect/locale/bs/LC_MESSAGES/django.mo
pxd_massaffect/locale/bs/LC_MESSAGES/django.po
pxd_massaffect/locale/ca/LC_MESSAGES/django.mo
pxd_massaffect/locale/ca/LC_MESSAGES/django.po
pxd_massaffect/locale/cs/LC_MESSAGES/django.mo
pxd_massaffect/locale/cs/LC_MESSAGES/django.po
pxd_massaffect/locale/cy/LC_MESSAGES/django.mo
pxd_massaffect/locale/cy/LC_MESSAGES/django.po
pxd_massaffect/locale/da/LC_MESSAGES/django.mo
pxd_massaffect/locale/da/LC_MESSAGES/django.po
pxd_massaffect/locale/de/LC_MESSAGES/django.mo
pxd_massaffect/locale/de/LC_MESSAGES/django.po
pxd_massaffect/locale/dsb/LC_MESSAGES/django.mo
pxd_massaffect/locale/dsb/LC_MESSAGES/django.po
pxd_massaffect/locale/el/LC_MESSAGES/django.mo
pxd_massaffect/locale/el/LC_MESSAGES/django.po
pxd_massaffect/locale/en/LC_MESSAGES/django.mo
pxd_massaffect/locale/en/LC_MESSAGES/django.po
